yaqn/.DS_Store
yaqn/.vscode/settings.json
yaqn/__init__.py
yaqn/about.py
yaqn/assets/logo_high_res.png
yaqn/assets/logo_low_res.png
yaqn/assets.py
yaqn/config.py
yaqn/gui.py
yaqn/main.py
yaqn/notes.py
yaqn/terminal.py
yaqn-1.9.0.dist-info/entry_points.txt
yaqn-1.9.0.dist-info/LICENSE.txt
yaqn-1.9.0.dist-info/WHEEL
yaqn-1.9.0.dist-info/METADATA
yaqn-1.9.0.dist-info/RECORD
