Metadata-Version: 2.1
Name: yaqn
Version: 1.9.0
Summary: A quicknotes app made in python and tkinter.
Home-page: https://github.com/kutu-dev/yaqn
License: MIT
Keywords: notes,utility,portable
Author: kutu-dev
Requires-Python: >=3.11,<4.0
Classifier: Development Status :: 5 - Production/Stable
Classifier: License :: OSI Approved :: MIT License
Classifier: Operating System :: OS Independent
Classifier: Programming Language :: Python :: 3
Classifier: Programming Language :: Python :: 3.11
Classifier: Topic :: Utilities
Project-URL: Repository, https://github.com/kutu-dev/yaqn
